hc_upgrade_tools/__init__.py
hc_upgrade_tools/handl_upgrade.py
hc_upgrade_tools/skeleton.py
hc_upgrade_tools/subcmd.py
hc_upgrade_tools/utility.py
hc_upgrade_tools-0.2.14.dist-info/LICENSE.txt
hc_upgrade_tools-0.2.14.dist-info/METADATA
hc_upgrade_tools-0.2.14.dist-info/WHEEL
hc_upgrade_tools-0.2.14.dist-info/entry_points.txt
hc_upgrade_tools-0.2.14.dist-info/top_level.txt
hc_upgrade_tools-0.2.14.dist-info/RECORD
