Metadata-Version: 2.1
Name: hc-upgrade-tools
Version: 0.2.14
Summary: Add a short description here!
Home-page: https://github.com/pyscaffold/pyscaffold/
Author: shixukai
Author-email: xukai.shi@hcrobots.com
License: MIT
Project-URL: Documentation, https://pyscaffold.org/
Platform: any
Classifier: Development Status :: 4 - Beta
Classifier: Programming Language :: Python
Requires-Python: >=3.7
License-File: LICENSE.txt
Requires-Dist: importlib-metadata ; python_version >= "3.7"
Requires-Dist: pip ; python_version >= "3.7"
Provides-Extra: testing
Requires-Dist: setuptools ; extra == 'testing'
Requires-Dist: pytest ; extra == 'testing'
Requires-Dist: pytest-cov ; extra == 'testing'
